README.md
setup.cfg
setup.py
django_cprofile_middleware/__init__.py
django_cprofile_middleware/middleware.py
django_cprofile_middleware_dmw.egg-info/PKG-INFO
django_cprofile_middleware_dmw.egg-info/SOURCES.txt
django_cprofile_middleware_dmw.egg-info/dependency_links.txt
django_cprofile_middleware_dmw.egg-info/top_level.txt