Metadata-Version: 1.1
Name: django-cprofile-middleware-dmw
Version: 0.3
Summary: Easily add cProfile profiling to django views.
Home-page: https://github.com/omarish/django-cprofile-middleware/
Author: Omar Bohsali
Author-email: omar.bohsali@gmail.com
License: MIT
Download-URL: https://github.com/omarish/django-cprofile-middleware/tarball/0.1
Keywords: django,profiling,cProfile
Platform: UNKNOWN
